SerialNumberGenerator/__init__.py
SerialNumberGenerator/main.py
PySerialNumberGenerator-0.4.0.dist-info/LICENSE
PySerialNumberGenerator-0.4.0.dist-info/METADATA
PySerialNumberGenerator-0.4.0.dist-info/WHEEL
PySerialNumberGenerator-0.4.0.dist-info/top_level.txt
PySerialNumberGenerator-0.4.0.dist-info/RECORD
