Metadata-Version: 2.1
Name: PySerialNumberGenerator
Version: 0.4.0
Summary: A brief description of your package
Home-page: 
Author: Your Name
Author-email: your.email@example.com
Classifier: Programming Language :: Python :: 3
Classifier: License :: OSI Approved :: MIT License
Classifier: Operating System :: OS Independent
Requires-Python: >=3.6
License-File: LICENSE
